degoogle/__init__.py
degoogle/degoogle.py
degoogle-1.0.1.dist-info/LICENSE
degoogle-1.0.1.dist-info/METADATA
degoogle-1.0.1.dist-info/WHEEL
degoogle-1.0.1.dist-info/entry_points.txt
degoogle-1.0.1.dist-info/top_level.txt
degoogle-1.0.1.dist-info/RECORD
