Metadata-Version: 2.1
Name: degoogle
Version: 1.0.1
Summary: Search and extract google results.
Home-page: https://github.com/deepseagirl/degoogle
Author: deepseagirl
License: UNKNOWN
Platform: UNKNOWN
Classifier: Programming Language :: Python :: 3
Classifier: Operating System :: OS Independent
Requires-Python: >=3.6
Requires-Dist: requests
